pagination/__init__.py
pagination/middleware.py
pagination/paginator.py
pagination/locale/cs/LC_MESSAGES/django.mo
pagination/locale/cs/LC_MESSAGES/django.po
pagination/locale/de/LC_MESSAGES/django.mo
pagination/locale/de/LC_MESSAGES/django.po
pagination/locale/es/LC_MESSAGES/django.mo
pagination/locale/es/LC_MESSAGES/django.po
pagination/locale/fr/LC_MESSAGES/django.mo
pagination/locale/fr/LC_MESSAGES/django.po
pagination/locale/pl/LC_MESSAGES/django.mo
pagination/locale/pl/LC_MESSAGES/django.po
pagination/locale/pt/LC_MESSAGES/django.mo
pagination/locale/pt/LC_MESSAGES/django.po
pagination/locale/pt_BR/LC_MESSAGES/django.mo
pagination/locale/pt_BR/LC_MESSAGES/django.po
pagination/templates/pagination/pagination.html
pagination/templatetags/__init__.py
pagination/templatetags/pagination_tags.py
django_pagination_py3-2.1.0.dist-info/METADATA
django_pagination_py3-2.1.0.dist-info/WHEEL
django_pagination_py3-2.1.0.dist-info/licenses/LICENSE.md
django_pagination_py3-2.1.0.dist-info/RECORD
