Metadata-Version: 2.3
Name: django-pagination-py3
Version: 2.1.0
Summary: A port of ericflo/django-pagination to Python 3 and beyond!
Project-URL: Homepage, https://matagus.github.io/django-pagination-py3
Project-URL: Documentation, https://matagus.github.io/django-pagination-py3
Project-URL: Issues, https://github.com/matagus/django-pagination-py3/issues
Project-URL: Changelog, https://github.com/matagus/django-pagination-py3/releases
Project-URL: Repository, https://github.com/matagus/django-pagination-py3
Project-URL: PyPI, https://pypi.org/project/django-pagination-py3
Author-email: Agustin Mendez <matagus@gmail.com>
License-Expression: BSD-2-Clause
License-File: LICENSE.md
Keywords: django,pagination
Classifier: Development Status :: 5 - Production/Stable
Classifier: Environment :: Console
Classifier: Environment :: Web Environment
Classifier: Framework :: Django
Classifier: Framework :: Django :: 4.0
Classifier: Framework :: Django :: 4.1
Classifier: Framework :: Django :: 4.2
Classifier: Framework :: Django :: 5.0
Classifier: Intended Audience :: Developers
Classifier: License :: OSI Approved :: BSD License
Classifier: Natural Language :: English
Classifier: Programming Language :: Python
Classifier: Programming Language :: Python :: 3.9
Classifier: Programming Language :: Python :: 3.10
Classifier: Programming Language :: Python :: 3.11
Classifier: Programming Language :: Python :: 3.12
Classifier: Programming Language :: Python :: 3.13
Classifier: Programming Language :: Python :: Implementation :: CPython
Classifier: Programming Language :: Python :: Implementation :: PyPy
Classifier: Topic :: Software Development :: Libraries
Classifier: Topic :: Software Development :: Libraries :: Python Modules
Requires-Dist: django>=4.0
Provides-Extra: dev
Requires-Dist: coverage[toml]; extra == 'dev'
Requires-Dist: ipdb; extra == 'dev'
Requires-Dist: ipython; extra == 'dev'
Requires-Dist: mypy; extra == 'dev'
Requires-Dist: typing-extensions; extra == 'dev'
Provides-Extra: docs
Requires-Dist: mkdocs; extra == 'docs'
Requires-Dist: mkdocs-material; extra == 'docs'
Requires-Dist: pygments; extra == 'docs'
Requires-Dist: pymdown-extensions; extra == 'docs'
